LICENSE
pyproject.toml
readme.md
src/pycpio/__init__.py
src/pycpio/main.py
src/pycpio/pycpio.py
src/pycpio.egg-info/PKG-INFO
src/pycpio.egg-info/SOURCES.txt
src/pycpio.egg-info/dependency_links.txt
src/pycpio.egg-info/entry_points.txt
src/pycpio.egg-info/requires.txt
src/pycpio.egg-info/top_level.txt
src/pycpio/cpio/__init__.py
src/pycpio/cpio/archive.py
src/pycpio/cpio/chardev.py
src/pycpio/cpio/common.py
src/pycpio/cpio/data.py
src/pycpio/cpio/dir.py
src/pycpio/cpio/file.py
src/pycpio/cpio/symlink.py
src/pycpio/header/__init__.py
src/pycpio/header/cpioheader.py
src/pycpio/header/header_funcs.py
src/pycpio/header/headers.py
src/pycpio/masks/__init__.py
src/pycpio/masks/modes.py
src/pycpio/masks/permissions.py
src/pycpio/reader/__init__.py
src/pycpio/reader/reader.py
src/pycpio/writer/__init__.py
src/pycpio/writer/writer.py
tests/test_cpio.py